oneNeuron/__init__.py
oneNeuron/perceptron.py
premsai_pypi_premsaisahoo-0.0.6.dist-info/LICENSE
premsai_pypi_premsaisahoo-0.0.6.dist-info/METADATA
premsai_pypi_premsaisahoo-0.0.6.dist-info/WHEEL
premsai_pypi_premsaisahoo-0.0.6.dist-info/top_level.txt
premsai_pypi_premsaisahoo-0.0.6.dist-info/RECORD
