Metadata-Version: 2.1
Name: premsai-pypi-premsaisahoo
Version: 0.0.6
Summary: its an implimentation of Perceptron
Home-page: https://github.com/premsaisahoo/premsai_pypi
Author: premsaisahoo
Author-email: premsaisahoo@gmail.com
License: UNKNOWN
Project-URL: Bug Tracker, https://github.com/premsaisahoo/premsai_pypi/issues
Platform: UNKNOWN
Classifier: Programming Language :: Python :: 3
Classifier: License :: OSI Approved :: MIT License
Classifier: Operating System :: OS Independent
Requires-Python: >=3.7
License-File: LICENSE
Requires-Dist: numpy
Requires-Dist: tqdm
